certbot_nginx_unit/__init__.py
certbot_nginx_unit/configurator.py
certbot_nginx_unit/unitc.py
certbot_nginx_unit/tests/__init__.py
certbot_nginx_unit/tests/configurator_test.py
certbot_nginx_unit-1.1.0.dist-info/LICENSE
certbot_nginx_unit-1.1.0.dist-info/METADATA
certbot_nginx_unit-1.1.0.dist-info/WHEEL
certbot_nginx_unit-1.1.0.dist-info/entry_points.txt
certbot_nginx_unit-1.1.0.dist-info/top_level.txt
certbot_nginx_unit-1.1.0.dist-info/RECORD
