Metadata-Version: 2.1
Name: certbot-nginx-unit
Version: 1.1.0
Summary: Nginx Unit plugin for Certbot
Author-email: Manuel Baldassarri <m.baldassarri@gmail.com>
License: MIT License
Project-URL: Homepage, https://github.com/kea/certbot-nginx-unit
Project-URL: Issues, https://github.com/kea/certbot-nginx-unit/issues
Classifier: Programming Language :: Python :: 3
Classifier: Programming Language :: Python :: 3.9
Classifier: Programming Language :: Python :: 3.10
Classifier: Programming Language :: Python :: 3.11
Classifier: Programming Language :: Python :: 3.12
Classifier: License :: OSI Approved :: MIT License
Classifier: Intended Audience :: System Administrators
Classifier: Topic :: Security :: Cryptography
Classifier: Topic :: Internet :: WWW/HTTP
Classifier: Topic :: Security
Classifier: Topic :: System :: Installation/Setup
Classifier: Topic :: System :: Networking
Classifier: Topic :: System :: Systems Administration
Classifier: Topic :: Utilities
Classifier: Development Status :: 5 - Production/Stable
Classifier: Environment :: Plugins
Classifier: Operating System :: OS Independent
License-File: LICENSE
Requires-Dist: acme>=2.12.0.dev0
Requires-Dist: certbot>=2.12.0.dev0
